ALU/Modificacion/mux4_1.v
/// Multiplexor 4 a 1 con entradas de 1 bit
/// Forma: conductual (reg)
module mux4_1(output reg out, input wire a, b, c, d, input wire [1:0] S);
  /// Lista de sensibilidad
  always @(a or b or c or d or S) 
  /// No hace falta begin y end porque el always contiene una sola sentencia, el case
    case (S)  
      /// Dos bits en binario            
      2'b00: out = a;
      2'b01: out = b;
      2'b10: out = c;
      2'b11: out = d;
      default: out = 'bx; /// Desconocido en cualquier otro caso                   
    endcase
endmodule

/// Forma estructural (wire)
// module mux4_1(output wire out, input wire a, b, c, d, input wire [1:0] S);
//   assign out = S[1] ? (S[0] ? d : c) : (S[0] ? b : a);
//   /// Si S[1] es 0, se seleccionan las primeras dos entradas
//   /// Si S[1] es 1, se seleccionan las otras dos entradas
//   /// Si S[0] es 0, se selecciona la primera de las dos seleccionadas
// endmodule

MedinaQuinteroEsther_p01/PR1Modif/flags.v
/// Módulo para los flags
/// Estructural (wire)
module flags(output wire zero, carry, sign, input wire [3:0] R, input wire temporal_carry);
  assign zero = R ? 4'b0 : 4'b1;
  assign sign = R[3];
  assign carry = temporal_carry;
endmodule

ALU/Modificacion/mux2_4.v
/// Multiplexor con entradas de 4 bits
/// Estructural (wire)
module mux2_4(output wire [3:0] Out, input wire [3:0] A, input wire [3:0] B, input wire s);
  /// Operador ternario para asignar
  assign Out = s ? B : A;
endmodule

/// Conductual (reg)
// module mux2_4(output reg [3:0] Out, input wire [3:0] A, input wire [3:0] B, input wire s);
//   always @ (A, B, s)
//     case (s)
//       1'b0 : Out = A;
//       1'b1 : Out = B;
//     endcase
// endmodule

ALU/Modificacion/cl.v
/// Celda lógica
/// Estructural (wire)
// module cl(output wire out, input wire a, b, input wire [1:0] S);
//   /// Cables de salidas
//   wire and_out, or_out, xor_out, not_out;
//   /// Operaciones
//   and and1(and_out, a, b);
//   or or1(or_out, a, b);
//   xor xor1(xor_out, a, b);
//   not not1(not_out, a);
//   /// Multiplexor para selecionar
//   mux4_1 mux(out, and_out, or_out, xor_out, not_out, S);
// endmodule

/// Forma conductual (reg)
module cl(output reg out, input wire a, b, input wire [1:0] S);
  always @ (S or a or b)
    begin
      case (S)
        2'b00: out = a & b; /// Puerta and
        2'b01: out = a | b; /// Puerta or
        2'b10: out = a ^ b; /// Puerta xor
        2'b11: out = ~a; /// Puerta not
      endcase
    end
endmodule

MedinaQuinteroEsther_p01/PR1Modif/ul4.v
/// Unidad lógica de 4 bits
/// Forma estructural (wire)
module ul4(output wire[3:0] Out, input wire[3:0] A, input wire[3:0] B, input wire [1:0] S);
  cl cl0(Out[0], A[0], B[0], S); /// Primer bit
  cl cl1(Out[1], A[1], B[1], S); /// Segundo bit
  cl cl2(Out[2], A[2], B[2], S); /// Tercer bit
  cl cl3(Out[3], A[3], B[3], S); /// Cuarto bit
endmodule

VerilogPlayground/p05/fa_v1.v
//Sumador completo (full-adder) de tres entradas de 1 bit realizado a partir de puertas lógicas 
module fa(output wire sum, output wire c_out, input wire a, input wire b, input wire c_in);

endmodule

MedinaQuinteroEsther_p01/PR1Modif/sum4.v
/// Sumador completo de 4 bits
/// Usando full-adder
module sum4(output wire[3:0] S, output wire c_out, input wire[3:0] A, input wire[3:0] B, input wire c_in);
  /// c0 = c_in
  wire c1, c2, c3;
  fa fa0(c1, S[0], A[0], B[0], c_in);
  fa fa1(c2, S[1], A[1], B[1], c1);
  fa fa2(c3, S[2], A[2], B[2], c2);
  fa fa3(c_out, S[3], A[3], B[3], c3);
endmodule

/// Usando asignación y concatenación
// module sum4(output wire[3:0] S, output wire c_out, input wire[3:0] A, input wire[3:0] B, input wire c_in);
//   assign {c_out, S} = A + B + c_in;
// endmodule

ALU/Implementacion/compl1.v
/// Complemento a 1
/// Forma estructural (wire)
module compl1(output wire [3:0] Out, input wire [3:0] Inp, input wire cpl);
  /// Hace el complemento cuando cpl es 1
  xor xor0(Out[0], Inp[0], cpl);
  xor xor1(Out[1], Inp[1], cpl);
  xor xor2(Out[2], Inp[2], cpl);
  xor xor3(Out[3], Inp[3], cpl);
endmodule

/// Forma conductual (reg)
// module compl1(output reg [3:0] Out, input wire [3:0] Inp, input wire cpl);
//   always @ (cpl, Inp)
//     if (cpl == 1'b1)
//       Out = ~Inp;
//     else
//       Out = Inp;
// endmodule

MedinaQuinteroEsther_p01/PR1Modif/alu.v
/// Unidad aritmético-lógica
/// Forma estructural (wire)
module alu(output wire [3:0] R, output wire zero, carry, sign, input wire [3:0] A, B, input wire [1:0] ALUOp, input wire l);
  /// Cables de salidas
  wire [3:0] op1, op2, out_mux, out_sum, out_ul;
  wire op1_A, op2_B, cpl, cin0;
  wire temporal_carry;

  /// op1_A = AluOp[1] + l
  assign op1_A = ALUOp[1] | l;
  /// op2_B = AluOp[1] + AluOp[0] + l
  assign op2_B = ALUOp[1] | ALUOp[0] | l;
  /// cpl = ~l~AluOP[1] + l~AluOp[0]
  assign cpl = (~l & ~ALUOp[1]) | (~l & ALUOp[0]);
  /// cin0 = ~AluOp[1] + AluOp[0]
  assign cin0 = ~ALUOp[1] | ALUOp[0];

  /// Primer mux
  mux2_4 mux1(op1, 4'b0, A, op1_A);
  /// Segundo mux
  mux2_4 mux2(out_mux, A, B, op2_B);
  /// Complemento a 1
  compl1 compl(op2, out_mux, cpl);
  /// Sumador completo
  sum4 sum(out_sum, temporal_carry, op1, op2, cin0);
  /// Unidad lógica
  ul4 ul(out_ul, op1, op2, ALUOp);
  /// Tercer mux
  mux2_4 mux3(R, out_sum, out_ul, l);

  /// Zero y sign
  flags flags1(zero, carry, sign, R, temporal_carry);

endmodule

/// ¿Objetivo final? Hacer una alu que hace op con 2 operandos de 4 bits: a y b
/// Op aritmeticas (full adder)
    /// Complemento
    /// Suma
    /// Resta
/// Op logicas 
    /// Bit a bit   

/// Camino de datos: forma estructural
    /// Dos operandos, operación y selector (logica o aritmetica)
    /// Resultado, carry (si es que hay), zero (a 1 si sale cero), sign (bit + significativo)
    /// En azul los puertos (parte externa)
        /// En la cabecera
    /// De forma estructural
    /// Todo lo negro son cabls internos (crea las instancias)
    /// Las cajas son el resto de modulos (otros ficheros)
        /// Instanciar y conectar
    /// En rojo están los bits de control
        /// Tenemos que diseñarlo
        /// Vamos a suponer: suma
            /// Empezamos de atrás hacia delante:
                /// Si la l es 0 deja pasar el resultado del sumador
                /// Hay que usar el sum4, que recibe dos operandos
                /// Op1 = A, Op2 = B
                /// Tenemos que elegir bien de los primeros
                /// mux1: Decidimos si pasa un cero o la A (en nuestro caso A)
                /// mux2: Decidimos si pasa la A o la B (en nuestro caso la B)
                /// ¿Necesitamos complementar? No, cero en el complemento
            /// Las operaciones lógicas van siempre con A y B
                /// Excepto negar una
                /// Siempre pasamos A y B y no complementamos
            /// ¿Problemas? Resta y complemento
                /// Resta en binario: sumando el complemento a 2
                /// Ej: complemento a 2 de A: complemento a 1 de A + 1
                    /// Cero por arriba
                    /// A por abajo complementado
                    /// Usamos el acarreo e entrada de Cin0: le ponemos un 1

/// (!) Usar la tabla de la verdad (!)
    /// Sacar las ecuaciones
    /// Simplificar y sacar la función lógica
    /// Tiene todos los posibles casos

/// (!) Traer la tabla de casa (!)
/// (!) Traer las funciones de casa (!)

ALU/Implementacion/Playground/alu_tb_M1.v
// Testbench para modulo alu
`timescale 1 ns / 10 ps //Directiva que fija la unidad de tiempo de simulación y la precision de la unidad
module alu_tb;
//declaracion de señales
reg [1:0] t_Op;
reg t_l;
reg [3:0] t_A, t_B;
wire [3:0] t_R;
wire t_z, t_c, t_s;
integer errores;
//instancia del modulo a testear
alu mat(t_R, t_z, t_c, t_s, t_A, t_B, t_Op, t_l);
initial
begin
  $dumpfile("alu.vcd");
  $dumpvars;
  $monitor("tiempo=%0d A=%b B=%b L=%b Op=%b R=%b, Z=%b, C=%b, S=%b", $time, t_A, t_B, t_l, t_Op, t_R, t_z, t_c, t_s);

  errores = 0;
  t_l = 1'b0;
  repeat(2)
	begin
	t_Op = 2'b0;
	repeat(4)
		begin
		  t_A = 4'b0;
		  repeat(16) 
		  begin
			t_B = 4'b0;
			repeat(16) 
			begin
				# 2 check;
				t_B = t_B + 1;
			end
			t_A = t_A + 1;
		  end
		  t_Op = t_Op + 1;
		end
		t_l = t_l + 1;
	end
	$display("Encontradas %d operaciones erroneas", errores);
  //fin simulacion
  $finish;
end

// Tarea para hacer la comprobación automática de resultados
task check;
reg [4:0] result;
reg flag_zero, flag_carry, flag_sign;
begin
	// Si las operaciones son lógicas
	if (t_l)
	begin
		case (t_Op)
			2'b00: result[3:0] = t_A & t_B;
			2'b01: result[3:0] = t_A | t_B;
			2'b10: result[3:0] = t_A ^ t_B;
			2'b11: result[3:0] = ~t_A;
			default: $display("ERROR. Valor no esperado para t_Op: %b", t_Op);
		endcase
		flag_carry = 1'bx;
		flag_sign = 1'bx;
	end
	else
	begin
		case (t_Op)
			2'b00: result = t_A + 4'b0001;
			2'b01: result = (t_B ^4'b1111) + 4'b0001;
			2'b10: result = t_A + t_B;
			2'b11: result = t_A + ((t_B ^4'b1111) + 1);
			default: $display("ERROR. Valor no esperado para t_Op: %b", t_Op);
		endcase
		flag_carry = result[4];
		flag_sign = result[3];
		if (flag_sign !== t_s || flag_carry !== t_c)
		begin
			errores = errores + 1;
			$display("ERROR con operacion L=%b, OP=%b A=%b B=%b", t_l, t_Op, t_A, t_B);
			if (flag_sign !== t_s)
				$display("ERROR. Flag de signo esperado %b, obtenido %b", flag_sign, t_s);
			if (flag_carry !== t_c)
				$display("\tFlag de acarreo esperado %b, obtenido %b", flag_carry, t_c);
		end
	end

	flag_zero = ~| result[3:0];
	if (result[3:0] !== t_R || flag_zero !== t_z)
	begin
		errores = errores + 1;
		$display("ERROR con operacion L=%b, OP=%b A=%b B=%b", t_l, t_Op, t_A, t_B);
		if (result[3:0] !== t_R)
			$display("\tResultado esperado %b, obtenido %b", result[3:0], t_R);
		if (flag_zero !== t_z)
			$display("\tFlag de cero esperado %b, obtenido %b", flag_zero, t_z);
	end
end
endtask
endmodule

ALU/Modificacion/alu.vcd
$date
	Tue Nov  8 15:22:02 2022
$end
$version
	Icarus Verilog
$end
$timescale
	10ps
$end
$scope module alu_tb $end
$var wire 1 ! t_z $end
$var wire 1 " t_s $end
$var wire 1 # t_c $end
$var wire 4 $ t_R [3:0] $end
$var reg 4 % t_A [3:0] $end
$var reg 4 & t_B [3:0] $end
$var reg 2 ' t_Op [1:0] $end
$var reg 1 ( t_l $end
$var integer 32 ) errores [31:0] $end
$scope module mat $end
$var wire 4 * A [3:0] $end
$var wire 2 + ALUOp [1:0] $end
$var wire 4 , B [3:0] $end
$var wire 1 - cin0 $end
$var wire 1 . cpl $end
$var wire 1 ( l $end
$var wire 1 / op1_A $end
$var wire 1 0 op2_B $end
$var wire 1 ! zero $end
$var wire 1 1 temporal_carry $end
$var wire 1 " sign $end
$var wire 4 2 out_ul [3:0] $end
$var wire 4 3 out_sum [3:0] $end
$var wire 4 4 out_mux [3:0] $end
$var wire 4 5 op2 [3:0] $end
$var wire 4 6 op1 [3:0] $end
$var wire 1 # carry $end
$var wire 4 7 R [3:0] $end
$scope module compl $end
$var wire 1 . cpl $end
$var wire 4 8 Out [3:0] $end
$var wire 4 9 Inp [3:0] $end
$upscope $end
$scope module flags1 $end
$var wire 1 # carry $end
$var wire 1 ! zero $end
$var wire 1 1 temporal_carry $end
$var wire 1 " sign $end
$var wire 4 : R [3:0] $end
$upscope $end
$scope module mux1 $end
$var wire 4 ; A [3:0] $end
$var wire 4 < B [3:0] $end
$var wire 1 / s $end
$var wire 4 = Out [3:0] $end
$upscope $end
$scope module mux2 $end
$var wire 4 > A [3:0] $end
$var wire 4 ? B [3:0] $end
$var wire 1 0 s $end
$var wire 4 @ Out [3:0] $end
$upscope $end
$scope module mux3 $end
$var wire 1 ( s $end
$var wire 4 A Out [3:0] $end
$var wire 4 B B [3:0] $end
$var wire 4 C A [3:0] $end
$upscope $end
$scope module sum $end
$var wire 4 D A [3:0] $end
$var wire 4 E B [3:0] $end
$var wire 1 - c_in $end
$var wire 1 1 c_out $end
$var wire 1 F c3 $end
$var wire 1 G c2 $end
$var wire 1 H c1 $end
$var wire 4 I S [3:0] $end
$scope module fa0 $end
$var wire 1 J a $end
$var wire 1 K b $end
$var wire 1 - c_in $end
$var wire 1 L sum $end
$var wire 1 H c_out $end
$upscope $end
$scope module fa1 $end
$var wire 1 M a $end
$var wire 1 N b $end
$var wire 1 H c_in $end
$var wire 1 O sum $end
$var wire 1 G c_out $end
$upscope $end
$scope module fa2 $end
$var wire 1 P a $end
$var wire 1 Q b $end
$var wire 1 G c_in $end
$var wire 1 R sum $end
$var wire 1 F c_out $end
$upscope $end
$scope module fa3 $end
$var wire 1 S a $end
$var wire 1 T b $end
$var wire 1 F c_in $end
$var wire 1 U sum $end
$var wire 1 1 c_out $end
$upscope $end
$upscope $end
$scope module ul $end
$var wire 4 V A [3:0] $end
$var wire 4 W B [3:0] $end
$var wire 2 X S [1:0] $end
$var wire 4 Y Out [3:0] $end
$scope module cl0 $end
$var wire 2 Z S [1:0] $end
$var wire 1 [ a $end
$var wire 1 \ b $end
$var reg 1 ] out $end
$upscope $end
$scope module cl1 $end
$var wire 2 ^ S [1:0] $end
$var wire 1 _ a $end
$var wire 1 ` b $end
$var reg 1 a out $end
$upscope $end
$scope module cl2 $end
$var wire 2 b S [1:0] $end
$var wire 1 c a $end
$var wire 1 d b $end
$var reg 1 e out $end
$upscope $end
$scope module cl3 $end
$var wire 2 f S [1:0] $end
$var wire 1 g a $end
$var wire 1 h b $end
$var reg 1 i out $end
$upscope $end
$upscope $end
$upscope $end
$scope task check $end
$var reg 1 j flag_carry $end
$var reg 1 k flag_sign $end
$var reg 1 l flag_zero $end
$var reg 5 m result [4:0] $end
$upscope $end
$upscope $end
$scope module mux4_1 $end
$var wire 2 n S [1:0] $end
$var wire 1 o a $end
$var wire 1 p b $end
$var wire 1 q c $end
$var wire 1 r d $end
$var reg 1 s out $end
$upscope $end
$enddefinitions $end
#0
$dumpvars
xs
zr
zq
zp
zo
bz n
bx m
xl
xk
xj
0i
1h
0g
b0 f
0e
1d
0c
b0 b
0a
1`
0_
b0 ^
0]
1\
0[
b0 Z
b0 Y
b0 X
b1111 W
b0 V
0U
1T
0S
0R
1Q
0P
0O
1N
0M
0L
1K
0J
b0 I
1H
1G
1F
b1111 E
b0 D
b0 C
b0 B
b0 A
b0 @
b0 ?
b0 >
b0 =
b0 <
b0 ;
b0 :
b0 9
b1111 8
b0 7
b0 6
b1111 5
b0 4
b0 3
b0 2
11
00
0/
1.
1-
b0 ,
b0 +
b0 *
b0 )
0(
b0 '
b0 &
b0 %
b0 $
1#
0"
1!
$end
#200
b1 &
b1 ,
b1 ?
1l
0k
1j
b10000 m
#400
b10 &
b10 ,
b10 ?
#600
b11 &
b11 ,
b11 ?
#800
b100 &
b100 ,
b100 ?
#1000
b101 &
b101 ,
b101 ?
#1200
b110 &
b110 ,
b110 ?
#1400
b111 &
b111 ,
b111 ?
#1600
b1000 &
b1000 ,
b1000 ?
#1800
b1001 &
b1001 ,
b1001 ?
#2000
b1010 &
b1010 ,
b1010 ?
#2200
b1011 &
b1011 ,
b1011 ?
#2400
b1100 &
b1100 ,
b1100 ?
#2600
b1101 &
b1101 ,
b1101 ?
#2800
b1110 &
b1110 ,
b1110 ?
#3000
b1111 &
b1111 ,
b1111 ?
#3200
1"
0!
1U
0#
01
1R
0F
b1111 $
b1111 7
b1111 :
b1111 A
1O
0G
b1111 3
b1111 C
b1111 I
1L
0H
0K
0\
b1110 5
b1110 8
b1110 E
b1110 W
b1 4
b1 9
b1 @
b1 %
b1 *
b1 <
b1 >
b0 &
b0 ,
b0 ?
#3400
b1 &
b1 ,
b1 ?
0l
1k
0j
b1111 m
#3600
b10 &
b10 ,
b10 ?
#3800
b11 &
b11 ,
b11 ?
#4000
b100 &
b100 ,
b100 ?
#4200
b101 &
b101 ,
b101 ?
#4400
b110 &
b110 ,
b110 ?
#4600
b111 &
b111 ,
b111 ?
#4800
b1000 &
b1000 ,
b1000 ?
#5000
b1001 &
b1001 ,
b1001 ?
#5200
b1010 &
b1010 ,
b1010 ?
#5400
b1011 &
b1011 ,
b1011 ?
#5600
b1100 &
b1100 ,
b1100 ?
#5800
b1101 &
b1101 ,
b1101 ?
#6000
b1110 &
b1110 ,
b1110 ?
#6200
b1111 &
b1111 ,
b1111 ?
#6400
b1110 $
b1110 7
b1110 :
b1110 A
b1110 3
b1110 C
b1110 I
0L
1H
0N
0`
1K
1\
b1101 5
b1101 8
b1101 E
b1101 W
b10 4
b10 9
b10 @
b10 %
b10 *
b10 <
b10 >
b0 &
b0 ,
b0 ?
#6600
b1 &
b1 ,
b1 ?
b1110 m
#6800
b10 &
b10 ,
b10 ?
#7000
b11 &
b11 ,
b11 ?
#7200
b100 &
b100 ,
b100 ?
#7400
b101 &
b101 ,
b101 ?
#7600
b110 &
b110 ,
b110 ?
#7800
b111 &
b111 ,
b111 ?
#8000
b1000 &
b1000 ,
b1000 ?
#8200
b1001 &
b1001 ,
b1001 ?
#8400
b1010 &
b1010 ,
b1010 ?
#8600
b1011 &
b1011 ,
b1011 ?
#8800
b1100 &
b1100 ,
b1100 ?
#9000
b1101 &
b1101 ,
b1101 ?
#9200
b1110 &
b1110 ,
b1110 ?
#9400
b1111 &
b1111 ,
b1111 ?
#9600
b1101 $
b1101 7
b1101 :
b1101 A
0O
b1101 3
b1101 C
b1101 I
1L
0H
0K
0\
b1100 5
b1100 8
b1100 E
b1100 W
b11 4
b11 9
b11 @
b11 %
b11 *
b11 <
b11 >
b0 &
b0 ,
b0 ?
#9800
b1 &
b1 ,
b1 ?
b1101 m
#10000
b10 &
b10 ,
b10 ?
#10200
b11 &
b11 ,
b11 ?
#10400
b100 &
b100 ,
b100 ?
#10600
b101 &
b101 ,
b101 ?
#10800
b110 &
b110 ,
b110 ?
#11000
b111 &
b111 ,
b111 ?
#11200
b1000 &
b1000 ,
b1000 ?
#11400
b1001 &
b1001 ,
b1001 ?
#11600
b1010 &
b1010 ,
b1010 ?
#11800
b1011 &
b1011 ,
b1011 ?
#12000
b1100 &
b1100 ,
b1100 ?
#12200
b1101 &
b1101 ,
b1101 ?
#12400
b1110 &
b1110 ,
b1110 ?
#12600
b1111 &
b1111 ,
b1111 ?
#12800
b1100 $
b1100 7
b1100 :
b1100 A
1G
1R
b1100 3
b1100 C
b1100 I
0L
1H
0Q
0d
1N
1`
1K
1\
b1011 5
b1011 8
b1011 E
b1011 W
b100 4
b100 9
b100 @
b100 %
b100 *
b100 <
b100 >
b0 &
b0 ,
b0 ?
#13000
b1 &
b1 ,
b1 ?
b1100 m
#13200
b10 &
b10 ,
b10 ?
#13400
b11 &
b11 ,
b11 ?
#13600
b100 &
b100 ,
b100 ?
#13800
b101 &
b101 ,
b101 ?
#14000
b110 &
b110 ,
b110 ?
#14200
b111 &
b111 ,
b111 ?
#14400
b1000 &
b1000 ,
b1000 ?
#14600
b1001 &
b1001 ,
b1001 ?
#14800
b1010 &
b1010 ,
b1010 ?
#15000
b1011 &
b1011 ,
b1011 ?
#15200
b1100 &
b1100 ,
b1100 ?
#15400
b1101 &
b1101 ,
b1101 ?
#15600
b1110 &
b1110 ,
b1110 ?
#15800
b1111 &
b1111 ,
b1111 ?
#16000
0R
b1011 $
b1011 7
b1011 :
b1011 A
1O
0G
b1011 3
b1011 C
b1011 I
1L
0H
0K
0\
b1010 5
b1010 8
b1010 E
b1010 W
b101 4
b101 9
b101 @
b101 %
b101 *
b101 <
b101 >
b0 &
b0 ,
b0 ?
#16200
b1 &
b1 ,
b1 ?
b1011 m
#16400
b10 &
b10 ,
b10 ?
#16600
b11 &
b11 ,
b11 ?
#16800
b100 &
b100 ,
b100 ?
#17000
b101 &
b101 ,
b101 ?
#17200
b110 &
b110 ,
b110 ?
#17400
b111 &
b111 ,
b111 ?
#17600
b1000 &
b1000 ,
b1000 ?
#17800
b1001 &
b1001 ,
b1001 ?
#18000
b1010 &
b1010 ,
b1010 ?
#18200
b1011 &
b1011 ,
b1011 ?
#18400
b1100 &
b1100 ,
b1100 ?
#18600
b1101 &
b1101 ,
b1101 ?
#18800
b1110 &
b1110 ,
b1110 ?
#19000
b1111 &
b1111 ,
b1111 ?
#19200
b1010 $
b1010 7
b1010 :
b1010 A
b1010 3
b1010 C
b1010 I
0L
1H
0N
0`
1K
1\
b1001 5
b1001 8
b1001 E
b1001 W
b110 4
b110 9
b110 @
b110 %
b110 *
b110 <
b110 >
b0 &
b0 ,
b0 ?
#19400
b1 &
b1 ,
b1 ?
b1010 m
#19600
b10 &
b10 ,
b10 ?
#19800
b11 &
b11 ,
b11 ?
#20000
b100 &
b100 ,
b100 ?
#20200
b101 &
b101 ,
b101 ?
#20400
b110 &
b110 ,
b110 ?
#20600
b111 &
b111 ,
b111 ?
#20800
b1000 &
b1000 ,
b1000 ?
#21000
b1001 &
b1001 ,
b1001 ?
#21200
b1010 &
b1010 ,
b1010 ?
#21400
b1011 &
b1011 ,
b1011 ?
#21600
b1100 &
b1100 ,
b1100 ?
#21800
b1101 &
b1101 ,
b1101 ?
#22000
b1110 &
b1110 ,
b1110 ?
#22200
b1111 &
b1111 ,
b1111 ?
#22400
b1001 $
b1001 7
b1001 :
b1001 A
0O
b1001 3
b1001 C
b1001 I
1L
0H
0K
0\
b1000 5
b1000 8
b1000 E
b1000 W
b111 4
b111 9
b111 @
b111 %
b111 *
b111 <
b111 >
b0 &
b0 ,
b0 ?
#22600
b1 &
b1 ,
b1 ?
b1001 m
#22800
b10 &
b10 ,
b10 ?
#23000
b11 &
b11 ,
b11 ?
#23200
b100 &
b100 ,
b100 ?
#23400
b101 &
b101 ,
b101 ?
#23600
b110 &
b110 ,
b110 ?
#23800
b111 &
b111 ,
b111 ?
#24000
b1000 &
b1000 ,
b1000 ?
#24200
b1001 &
b1001 ,
b1001 ?
#24400
b1010 &
b1010 ,
b1010 ?
#24600
b1011 &
b1011 ,
b1011 ?
#24800
b1100 &
b1100 ,
b1100 ?
#25000
b1101 &
b1101 ,
b1101 ?
#25200
b1110 &
b1110 ,
b1110 ?
#25400
b1111 &
b1111 ,
b1111 ?
#25600
1"
1F
b1000 $
b1000 7
b1000 :
b1000 A
1G
1U
0R
b1000 3
b1000 C
b1000 I
0L
1H
0T
0h
1Q
1d
1N
1`
1K
1\
b111 5
b111 8
b111 E
b111 W
b1000 4
b1000 9
b1000 @
b1000 %
b1000 *
b1000 <
b1000 >
b0 &
b0 ,
b0 ?
#25800
b1 &
b1 ,
b1 ?
b1000 m
#26000
b10 &
b10 ,
b10 ?
#26200
b11 &
b11 ,
b11 ?
#26400
b100 &
b100 ,
b100 ?
#26600
b101 &
b101 ,
b101 ?
#26800
b110 &
b110 ,
b110 ?
#27000
b111 &
b111 ,
b111 ?
#27200
b1000 &
b1000 ,
b1000 ?
#27400
b1001 &
b1001 ,
b1001 ?
#27600
b1010 &
b1010 ,
b1010 ?
#27800
b1011 &
b1011 ,
b1011 ?
#28000
b1100 &
b1100 ,
b1100 ?
#28200
b1101 &
b1101 ,
b1101 ?
#28400
b1110 &
b1110 ,
b1110 ?
#28600
b1111 &
b1111 ,
b1111 ?
#28800
0"
0U
1R
0F
b111 $
b111 7
b111 :
b111 A
1O
0G
b111 3
b111 C
b111 I
1L
0H
0K
0\
b110 5
b110 8
b110 E
b110 W
b1001 4
b1001 9
b1001 @
b1001 %
b1001 *
b1001 <
b1001 >
b0 &
b0 ,
b0 ?
#29000
b1 &
b1 ,
b1 ?
0k
b111 m
#29200
b10 &
b10 ,
b10 ?
#29400
b11 &
b11 ,
b11 ?
#29600
b100 &
b100 ,
b100 ?
#29800
b101 &
b101 ,
b101 ?
#30000
b110 &
b110 ,
b110 ?
#30200
b111 &
b111 ,
b111 ?
#30400
b1000 &
b1000 ,
b1000 ?
#30600
b1001 &
b1001 ,
b1001 ?
#30800
b1010 &
b1010 ,
b1010 ?
#31000
b1011 &
b1011 ,
b1011 ?
#31200
b1100 &
b1100 ,
b1100 ?
#31400
b1101 &
b1101 ,
b1101 ?
#31600
b1110 &
b1110 ,
b1110 ?
#31800
b1111 &
b1111 ,
b1111 ?
#32000
b110 $
b110 7
b110 :
b110 A
b110 3
b110 C
b110 I
0L
1H
0N
0`
1K
1\
b101 5
b101 8
b101 E
b101 W
b1010 4
b1010 9
b1010 @
b1010 %
b1010 *
b1010 <
b1010 >
b0 &
b0 ,
b0 ?
#32200
b1 &
b1 ,
b1 ?
b110 m
#32400
b10 &
b10 ,
b10 ?
#32600
b11 &
b11 ,
b11 ?
#32800
b100 &
b100 ,
b100 ?
#33000
b101 &
b101 ,
b101 ?
#33200
b110 &
b110 ,
b110 ?
#33400
b111 &
b111 ,
b111 ?
#33600
b1000 &
b1000 ,
b1000 ?
#33800
b1001 &
b1001 ,
b1001 ?
#34000
b1010 &
b1010 ,
b1010 ?
#34200
b1011 &
b1011 ,
b1011 ?
#34400
b1100 &
b1100 ,
b1100 ?
#34600
b1101 &
b1101 ,
b1101 ?
#34800
b1110 &
b1110 ,
b1110 ?
#35000
b1111 &
b1111 ,
b1111 ?
#35200
b101 $
b101 7
b101 :
b101 A
0O
b101 3
b101 C
b101 I
1L
0H
0K
0\
b100 5
b100 8
b100 E
b100 W
b1011 4
b1011 9
b1011 @
b1011 %
b1011 *
b1011 <
b1011 >
b0 &
b0 ,
b0 ?
#35400
b1 &
b1 ,
b1 ?
b101 m
#35600
b10 &
b10 ,
b10 ?
#35800
b11 &
b11 ,
b11 ?
#36000
b100 &
b100 ,
b100 ?
#36200
b101 &
b101 ,
b101 ?
#36400
b110 &
b110 ,
b110 ?
#36600
b111 &
b111 ,
b111 ?
#36800
b1000 &
b1000 ,
b1000 ?
#37000
b1001 &
b1001 ,
b1001 ?
#37200
b1010 &
b1010 ,
b1010 ?
#37400
b1011 &
b1011 ,
b1011 ?
#37600
b1100 &
b1100 ,
b1100 ?
#37800
b1101 &
b1101 ,
b1101 ?
#38000
b1110 &
b1110 ,
b1110 ?
#38200
b1111 &
b1111 ,
b1111 ?
#38400
0!
b100 $
b100 7
b100 :
b100 A
1G
1R
b100 3
b100 C
b100 I
0L
1H
0Q
0d
1N
1`
1K
1\
b11 5
b11 8
b11 E
b11 W
b1100 4
b1100 9
b1100 @
b1100 %
b1100 *
b1100 <
b1100 >
b0 &
b0 ,
b0 ?
#38600
b1 &
b1 ,
b1 ?
b100 m
#38800
b10 &
b10 ,
b10 ?
#39000
b11 &
b11 ,
b11 ?
#39200
b100 &
b100 ,
b100 ?
#39400
b101 &
b101 ,
b101 ?
#39600
b110 &
b110 ,
b110 ?
#39800
b111 &
b111 ,
b111 ?
#40000
b1000 &
b1000 ,
b1000 ?
#40200
b1001 &
b1001 ,
b1001 ?
#40400
b1010 &
b1010 ,
b1010 ?
#40600
b1011 &
b1011 ,
b1011 ?
#40800
b1100 &
b1100 ,
b1100 ?
#41000
b1101 &
b1101 ,
b1101 ?
#41200
b1110 &
b1110 ,
b1110 ?
#41400
b1111 &
b1111 ,
b1111 ?
#41600
0R
b11 $
b11 7
b11 :
b11 A
1O
0G
b11 3
b11 C
b11 I
1L
0H
0K
0\
b10 5
b10 8
b10 E
b10 W
b1101 4
b1101 9
b1101 @
b1101 %
b1101 *
b1101 <
b1101 >
b0 &
b0 ,
b0 ?
#41800
b1 &
b1 ,
b1 ?
b11 m
#42000
b10 &
b10 ,
b10 ?
#42200
b11 &
b11 ,
b11 ?
#42400
b100 &
b100 ,
b100 ?
#42600
b101 &
b101 ,
b101 ?
#42800
b110 &
b110 ,
b110 ?
#43000
b111 &
b111 ,
b111 ?
#43200
b1000 &
b1000 ,
b1000 ?
#43400
b1001 &
b1001 ,
b1001 ?
#43600
b1010 &
b1010 ,
b1010 ?
#43800
b1011 &
b1011 ,
b1011 ?
#44000
b1100 &
b1100 ,
b1100 ?
#44200
b1101 &
b1101 ,
b1101 ?
#44400
b1110 &
b1110 ,
b1110 ?
#44600
b1111 &
b1111 ,
b1111 ?
#44800
b10 $
b10 7
b10 :
b10 A
b10 3
b10 C
b10 I
0L
1H
0N
0`
1K
1\
b1 5
b1 8
b1 E
b1 W
b1110 4
b1110 9
b1110 @
b1110 %
b1110 *
b1110 <
b1110 >
b0 &
b0 ,
b0 ?
#45000
b1 &
b1 ,
b1 ?
b10 m
#45200
b10 &
b10 ,
b10 ?
#45400
b11 &
b11 ,
b11 ?
#45600
b100 &
b100 ,
b100 ?
#45800
b101 &
b101 ,
b101 ?
#46000
b110 &
b110 ,
b110 ?
#46200
b111 &
b111 ,
b111 ?
#46400
b1000 &
b1000 ,
b1000 ?
#46600
b1001 &
b1001 ,
b1001 ?
#46800
b1010 &
b1010 ,
b1010 ?
#47000
b1011 &
b1011 ,
b1011 ?
#47200
b1100 &
b1100 ,
b1100 ?
#47400
b1101 &
b1101 ,
b1101 ?
#47600
b1110 &
b1110 ,
b1110 ?
#47800
b1111 &
b1111 ,
b1111 ?
#48000
b1 $
b1 7
b1 :
b1 A
0O
b1 3
b1 C
b1 I
1L
0H
0K
0\
b0 5
b0 8
b0 E
b0 W
b1111 4
b1111 9
b1111 @
b1111 %
b1111 *
b1111 <
b1111 >
b0 &
b0 ,
b0 ?
#48200
b1 &
b1 ,
b1 ?
b1 m
#48400
b10 &
b10 ,
b10 ?
#48600
b11 &
b11 ,
b11 ?
#48800
b100 &
b100 ,
b100 ?
#49000
b101 &
b101 ,
b101 ?
#49200
b110 &
b110 ,
b110 ?
#49400
b111 &
b111 ,
b111 ?
#49600
b1000 &
b1000 ,
b1000 ?
#49800
b1001 &
b1001 ,
b1001 ?
#50000
b1010 &
b1010 ,
b1010 ?
