VerilogPlayground/p01/ha_v1.v
/// Semisumador de dos entradas de 1 bit realizado a partir de puertas

module ha_v1(output wire sum, carry, input wire a, b);
/// Declaración de conexiones internas: no hay ninguna
/// Estructura interna: Instancias de puertas y sus conexiones
xor xor1(sum, a, b);
and and1(carry, a, b);
endmodule

VerilogPlayground/p01/adder.v
/// Adder usando hafl adder
module adder (output wire sum2, cout, input wire cin, a, b);
  wire sum1, carry1, carry2;
  /// Primer semisumador
        // xor xor1(sum1, a, b);
        // and and1(carry2, a, b);
  ha_v1 ha1(sum1, carry1, a, b);
  /// Segundo semisumador
        // xor xor2(sum2, cin, sum1);
        // and and2(carry2, cin, sum1);
  ha_v1 ha2(sum2, carry2, cin, sum1);
  /// El or
  or or1(cout, carry1, carry2);
endmodule

VerilogPlayground/p01/adder_tb.v
/// Testbench para módulo semisumador visto antes

/// ` Esa cosa significa directiva de verilog
/// Es para los retardos
/// Unidad de tiempo con la que se leen los retardos
/// Escala / Precisión
/// Por debajo de precisión no va a detectar cambios
`timescale 1 ns / 10 ps

/// NO tiene entradas ni salidas
module adder_tb; 

/// Son reg porque les damos valor dentro de una estructura
/// Es reg porque es conductual
reg test_cin, test_a, test_b; 
/// No tiene que ver con el otro fichero
/// Es wire porque es estructual
wire test_cout, test_sum2;

/// Módulo que queremos probar
adder adder(test_sum2, test_cout, test_cin, test_a, test_a); 

/// Probamos todas las combinaciones
/// Initial ejecuta todos en paralelo nada más empezar la simulación
/// Always ejecuta todo el rato
/// Podríamos tener varios initial
initial 
begin
  /// Es como un print
  /// Cada vez que cambia el valor de alguna señal, imprime
  $monitor("tiempo=%0d a=%b b=%b cin=%b resultado=%b cout=%b", $time, test_a, test_b, test_cin, test_sum2, test_cout);
  /// Estos dos son para visualizar
  /// dumpfile: traza
  /// dumpvars: qué queremos guardar en la traza (sin nada, guarda todo)
  /// Comando: gtkwave ejemplo_tb.vcd &
  $dumpfile("adder_tb.vcd");
  $dumpvars;

  test_cin = 1'b0;

  /// Test: a = 0; b = 0
  test_a = 1'b0; /// Tamaño ' base valor
  test_b = 1'b0;
  #20; /// Retardo (20 x 1)

  /// Test: a = 0; b = 1
  test_a = 1'b0;
  test_b = 1'b1;
  #20; /// Retardo (20 x 1)

  /// Test: a = 1; b = 0
  test_a = 1'b1;
  test_b = 1'b0;
  #20; /// Retardo (20 x 1)

  /// Test: a = 1; b = 1
  test_a = 1'b1;
  test_b = 1'b1;
  #20; /// Retardo (20 x 1)

  test_cin = 1'b1;

  /// Test: a = 0; b = 0
  test_a = 1'b0; /// Tamaño ' base valor
  test_b = 1'b0;
  #20; /// Retardo (20 x 1)

  /// Test: a = 0; b = 1
  test_a = 1'b0;
  test_b = 1'b1;
  #20; /// Retardo (20 x 1)

  /// Test: a = 1; b = 0
  test_a = 1'b1;
  test_b = 1'b0;
  #20; /// Retardo (20 x 1)

  /// Test: a = 1; b = 1
  test_a = 1'b1;
  test_b = 1'b1;
  #20; /// Retardo (20 x 1)

  /// Todos los comandos internos de verilog tienen un $
  /// Si no lo ponemos, no salimos del entorno
  $finish;  

end
endmodule

VerilogPlayground/p01/adder_tb.vcd
$date
	Tue Oct 11 14:23:47 2022
$end
$version
	Icarus Verilog
$end
$timescale
	10ps
$end
$scope module adder_tb $end
$var wire 1 ! test_sum2 $end
$var wire 1 " test_cout $end
$var reg 1 # test_a $end
$var reg 1 $ test_b $end
$var reg 1 % test_cin $end
$scope module adder $end
$var wire 1 # a $end
$var wire 1 # b $end
$var wire 1 % cin $end
$var wire 1 " cout $end
$var wire 1 ! sum2 $end
$var wire 1 & sum1 $end
$var wire 1 ' carry2 $end
$var wire 1 ( carry1 $end
$scope module ha1 $end
$var wire 1 # a $end
$var wire 1 # b $end
$var wire 1 ( carry $end
$var wire 1 & sum $end
$upscope $end
$scope module ha2 $end
$var wire 1 % a $end
$var wire 1 & b $end
$var wire 1 ' carry $end
$var wire 1 ! sum $end
$upscope $end
$upscope $end
$upscope $end
$enddefinitions $end
#0
$dumpvars
0(
0'
0&
0%
0$
0#
0"
0!
$end
#2000
1$
#4000
1"
1(
0$
1#
#6000
1$
#8000
0"
0(
1!
0$
0#
1%
#10000
1$
#12000
1"
1(
0$
1#
#14000
1$
