ALU/Modificacion/mux4_1.v
/// Multiplexor 4 a 1 con entradas de 1 bit
/// Forma: conductual (reg)
module mux4_1(output reg out, input wire a, b, c, d, input wire [1:0] S);
  /// Lista de sensibilidad
  always @(a or b or c or d or S) 
  /// No hace falta begin y end porque el always contiene una sola sentencia, el case
    case (S)  
      /// Dos bits en binario            
      2'b00: out = a;
      2'b01: out = b;
      2'b10: out = c;
      2'b11: out = d;
      default: out = 'bx; /// Desconocido en cualquier otro caso                   
    endcase
endmodule

/// Forma estructural (wire)
// module mux4_1(output wire out, input wire a, b, c, d, input wire [1:0] S);
//   assign out = S[1] ? (S[0] ? d : c) : (S[0] ? b : a);
//   /// Si S[1] es 0, se seleccionan las primeras dos entradas
//   /// Si S[1] es 1, se seleccionan las otras dos entradas
//   /// Si S[0] es 0, se selecciona la primera de las dos seleccionadas
// endmodule

ALU/Implementacion/cl.v
/// Celda lógica
/// Estructural (wire)
module cl(output wire out, input wire a, b, input wire [1:0] S);
  /// Cables de salidas
  wire and_out, or_out, xor_out, not_out;
  /// Operaciones
  and and1(and_out, a, b);
  or or1(or_out, a, b);
  xor xor1(xor_out, a, b);
  not not1(not_out, a);
  /// Multiplexor para selecionar
  mux4_1 mux(out, and_out, or_out, xor_out, not_out, S);
endmodule

/// Forma conductual (reg)

MedinaQuinteroEsther_p01/PR1Modif/ul4.v
/// Unidad lógica de 4 bits
/// Forma estructural (wire)
module ul4(output wire[3:0] Out, input wire[3:0] A, input wire[3:0] B, input wire [1:0] S);
  cl cl0(Out[0], A[0], B[0], S); /// Primer bit
  cl cl1(Out[1], A[1], B[1], S); /// Segundo bit
  cl cl2(Out[2], A[2], B[2], S); /// Tercer bit
  cl cl3(Out[3], A[3], B[3], S); /// Cuarto bit
endmodule

MedinaQuinteroEsther_p01/PR1Modif/Test/ul4_tb.v
/// ` Esa cosa significa directiva de verilog
/// Es para los retardos
/// Unidad de tiempo con la que se leen los retardos
/// Escala / Precisión
/// Por debajo de precisión no va a detectar cambios
`timescale 1 ns / 10 ps

/// NO tiene entradas ni salidas
module ul4_tb; 

/// Son reg porque les damos valor dentro de una estructura
/// Es reg porque es conductual
reg [1:0] test_S;
reg [3:0] test_A, test_B; 
/// No tiene que ver con el otro fichero
/// Es wire porque es estructual
wire [3:0] test_Out;

/// Módulo que queremos probar
ul4 ul4(test_Out, test_A, test_B, test_S); 

/// Probamos todas las combinaciones
/// Initial ejecuta todos en paralelo nada más empezar la simulación
/// Always ejecuta todo el rato
/// Podríamos tener varios initial
initial 
begin
  /// Es como un print
  /// Cada vez que cambia el valor de alguna señal, imprime
  $monitor("A(%b) B(%b) S(%b) out(%b)", test_A, test_B, test_S, test_Out);
  /// Estos dos son para visualizar
  /// dumpfile: traza
  /// dumpvars: qué queremos guardar en la traza (sin nada, guarda todo)
  /// Comando: gtkwave ejemplo_tb.vcd &
  $dumpfile("ul4_tb.vcd");
  $dumpvars;

  /// And: S = 00
  test_S = 2'b00;
  /// Test: a = 0; b = 0; 
  test_A = 4'b0010;
  test_B = 4'b1010;
  #20; /// Retardo (20 x 1)
  /// Test: a = 1; b = 1; s = 00
  test_A = 4'b0000;
  test_B = 4'b0000;
  #20; /// Retardo (20 x 1)

  /// Or: S = 01
  test_S = 2'b01;
  /// Test: a = 0; b = 0; 
  test_A = 4'b0010;
  test_B = 4'b1010;
  #20; /// Retardo (20 x 1)
  /// Test: a = 1; b = 1; s = 00
  test_A = 4'b0000;
  test_B = 4'b0000;
  #20; /// Retardo (20 x 1)

  /// Xor: S = 10
  test_S = 2'b10;
  /// Test: a = 0; b = 0; 
  test_A = 4'b0010;
  test_B = 4'b1010;
  #20; /// Retardo (20 x 1)
  /// Test: a = 1; b = 1; s = 00
  test_A = 4'b0000;
  test_B = 4'b0000;
  #20; /// Retardo (20 x 1)

  /// Not: S = 11
  test_S = 2'b11;
  /// Test: a = 0; b = 0; 
  test_A = 4'b0010;
  #20; /// Retardo (20 x 1)
  /// Test: a = 1; b = 1; s = 00
  test_A = 4'b0000;
  #20; /// Retardo (20 x 1)

  /// Todos los comandos internos de verilog tienen un $
  /// Si no lo ponemos, no salimos del entorno
  $finish;  

end
endmodule

ALU/Implementacion/Test/ul4_tb.vcd
$date
	Mon Oct 31 01:09:55 2022
$end
$version
	Icarus Verilog
$end
$timescale
	10ps
$end
$scope module ul4_tb $end
$var wire 4 ! test_Out [3:0] $end
$var reg 4 " test_A [3:0] $end
$var reg 4 # test_B [3:0] $end
$var reg 2 $ test_S [1:0] $end
$scope module ul4 $end
$var wire 4 % A [3:0] $end
$var wire 4 & B [3:0] $end
$var wire 2 ' S [1:0] $end
$var wire 4 ( Out [3:0] $end
$scope module cl0 $end
$var wire 2 ) S [1:0] $end
$var wire 1 * a $end
$var wire 1 + and_out $end
$var wire 1 , b $end
$var wire 1 - not_out $end
$var wire 1 . or_out $end
$var wire 1 / xor_out $end
$var wire 1 0 out $end
$scope module mux $end
$var wire 2 1 S [1:0] $end
$var wire 1 + a $end
$var wire 1 . b $end
$var wire 1 / c $end
$var wire 1 - d $end
$var reg 1 0 out $end
$upscope $end
$upscope $end
$scope module cl1 $end
$var wire 2 2 S [1:0] $end
$var wire 1 3 a $end
$var wire 1 4 and_out $end
$var wire 1 5 b $end
$var wire 1 6 not_out $end
$var wire 1 7 or_out $end
$var wire 1 8 xor_out $end
$var wire 1 9 out $end
$scope module mux $end
$var wire 2 : S [1:0] $end
$var wire 1 4 a $end
$var wire 1 7 b $end
$var wire 1 8 c $end
$var wire 1 6 d $end
$var reg 1 9 out $end
$upscope $end
$upscope $end
$scope module cl2 $end
$var wire 2 ; S [1:0] $end
$var wire 1 < a $end
$var wire 1 = and_out $end
$var wire 1 > b $end
$var wire 1 ? not_out $end
$var wire 1 @ or_out $end
$var wire 1 A xor_out $end
$var wire 1 B out $end
$scope module mux $end
$var wire 2 C S [1:0] $end
$var wire 1 = a $end
$var wire 1 @ b $end
$var wire 1 A c $end
$var wire 1 ? d $end
$var reg 1 B out $end
$upscope $end
$upscope $end
$scope module cl3 $end
$var wire 2 D S [1:0] $end
$var wire 1 E a $end
$var wire 1 F and_out $end
$var wire 1 G b $end
$var wire 1 H not_out $end
$var wire 1 I or_out $end
$var wire 1 J xor_out $end
$var wire 1 K out $end
$scope module mux $end
$var wire 2 L S [1:0] $end
$var wire 1 F a $end
$var wire 1 I b $end
$var wire 1 J c $end
$var wire 1 H d $end
$var reg 1 K out $end
$upscope $end
$upscope $end
$upscope $end
$upscope $end
$enddefinitions $end
#0
$dumpvars
b0 L
0K
1J
1I
1H
1G
0F
0E
b0 D
b0 C
0B
0A
0@
1?
0>
0=
0<
b0 ;
b0 :
19
08
17
06
15
14
13
b0 2
b0 1
00
0/
0.
1-
0,
0+
0*
b0 )
b10 (
b0 '
b1010 &
b10 %
b0 $
b1010 #
b10 "
b10 !
$end
#2000
b0 !
b0 (
09
0I
0J
04
07
16
05
0G
03
b0 #
b0 &
b0 "
b0 %
#4000
1K
b1010 !
b1010 (
19
1I
1J
14
17
06
15
1G
13
b1010 #
b1010 &
b10 "
b10 %
b1 $
b1 '
b1 )
b1 1
b1 2
b1 :
b1 ;
b1 C
b1 D
b1 L
#6000
0K
b0 !
b0 (
09
0I
0J
04
07
16
05
0G
03
b0 #
b0 &
b0 "
b0 %
#8000
b1000 !
b1000 (
1K
1I
1J
14
17
06
15
1G
13
b1010 #
b1010 &
b10 "
b10 %
b10 $
b10 '
b10 )
b10 1
b10 2
b10 :
b10 ;
b10 C
b10 D
b10 L
#10000
b0 !
b0 (
0K
0I
0J
04
07
16
05
0G
03
b0 #
b0 &
b0 "
b0 %
#12000
17
18
06
13
10
09
1B
b1101 !
b1101 (
1K
b10 "
b10 %
b11 $
b11 '
b11 )
b11 1
b11 2
b11 :
b11 ;
b11 C
b11 D
b11 L
#14000
b1111 !
b1111 (
19
07
08
16
03
b0 "
b0 %
