ALU/Modificacion/mux2_4.v
/// Multiplexor con entradas de 4 bits
/// Estructural (wire)
module mux2_4(output wire [3:0] Out, input wire [3:0] A, input wire [3:0] B, input wire s);
  /// Operador ternario para asignar
  assign Out = s ? B : A;
endmodule

/// Conductual (reg)
// module mux2_4(output reg [3:0] Out, input wire [3:0] A, input wire [3:0] B, input wire s);
//   always @ (A, B, s)
//     case (s)
//       1'b0 : Out = A;
//       1'b1 : Out = B;
//     endcase
// endmodule

ALU/Modificacion/mux4_1.v
/// Multiplexor 4 a 1 con entradas de 1 bit
/// Forma: conductual (reg)
module mux4_1(output reg out, input wire a, b, c, d, input wire [1:0] S);
  /// Lista de sensibilidad
  always @(a or b or c or d or S) 
  /// No hace falta begin y end porque el always contiene una sola sentencia, el case
    case (S)  
      /// Dos bits en binario            
      2'b00: out = a;
      2'b01: out = b;
      2'b10: out = c;
      2'b11: out = d;
      default: out = 'bx; /// Desconocido en cualquier otro caso                   
    endcase
endmodule

/// Forma estructural (wire)
// module mux4_1(output wire out, input wire a, b, c, d, input wire [1:0] S);
//   assign out = S[1] ? (S[0] ? d : c) : (S[0] ? b : a);
//   /// Si S[1] es 0, se seleccionan las primeras dos entradas
//   /// Si S[1] es 1, se seleccionan las otras dos entradas
//   /// Si S[0] es 0, se selecciona la primera de las dos seleccionadas
// endmodule

ALU/Implementacion/cl.v
/// Celda lógica
/// Estructural (wire)
module cl(output wire out, input wire a, b, input wire [1:0] S);
  /// Cables de salidas
  wire and_out, or_out, xor_out, not_out;
  /// Operaciones
  and and1(and_out, a, b);
  or or1(or_out, a, b);
  xor xor1(xor_out, a, b);
  not not1(not_out, a);
  /// Multiplexor para selecionar
  mux4_1 mux(out, and_out, or_out, xor_out, not_out, S);
endmodule

/// Forma conductual (reg)

MedinaQuinteroEsther_p01/PR1Modif/ul4.v
/// Unidad lógica de 4 bits
/// Forma estructural (wire)
module ul4(output wire[3:0] Out, input wire[3:0] A, input wire[3:0] B, input wire [1:0] S);
  cl cl0(Out[0], A[0], B[0], S); /// Primer bit
  cl cl1(Out[1], A[1], B[1], S); /// Segundo bit
  cl cl2(Out[2], A[2], B[2], S); /// Tercer bit
  cl cl3(Out[3], A[3], B[3], S); /// Cuarto bit
endmodule

VerilogPlayground/p05/fa_v1.v
//Sumador completo (full-adder) de tres entradas de 1 bit realizado a partir de puertas lógicas 
module fa(output wire sum, output wire c_out, input wire a, input wire b, input wire c_in);

endmodule

MedinaQuinteroEsther_p01/PR1Modif/sum4.v
/// Sumador completo de 4 bits
/// Usando full-adder
module sum4(output wire[3:0] S, output wire c_out, input wire[3:0] A, input wire[3:0] B, input wire c_in);
  /// c0 = c_in
  wire c1, c2, c3;
  fa fa0(c1, S[0], A[0], B[0], c_in);
  fa fa1(c2, S[1], A[1], B[1], c1);
  fa fa2(c3, S[2], A[2], B[2], c2);
  fa fa3(c_out, S[3], A[3], B[3], c3);
endmodule

/// Usando asignación y concatenación
// module sum4(output wire[3:0] S, output wire c_out, input wire[3:0] A, input wire[3:0] B, input wire c_in);
//   assign {c_out, S} = A + B + c_in;
// endmodule

ALU/Implementacion/compl1.v
/// Complemento a 1
/// Forma estructural (wire)
module compl1(output wire [3:0] Out, input wire [3:0] Inp, input wire cpl);
  /// Hace el complemento cuando cpl es 1
  xor xor0(Out[0], Inp[0], cpl);
  xor xor1(Out[1], Inp[1], cpl);
  xor xor2(Out[2], Inp[2], cpl);
  xor xor3(Out[3], Inp[3], cpl);
endmodule

/// Forma conductual (reg)
// module compl1(output reg [3:0] Out, input wire [3:0] Inp, input wire cpl);
//   always @ (cpl, Inp)
//     if (cpl == 1'b1)
//       Out = ~Inp;
//     else
//       Out = Inp;
// endmodule

ALU/Modificacion/Pruebas/aluM1.v
/// Modificación:
/// Cambiar el compl2(a) por A + 1

/// Unidad aritmético-lógica
/// Forma estructural (wire)
module alu(output wire [3:0] R, output wire zero, carry, sign, input wire [3:0] A, B, input wire [1:0] ALUOp, input wire l);
  /// Cables de salidas
  wire [3:0] op1, op2, out_mux, out1_sum, out2_sum;
  wire op1_A, op2_B, cpl, cin0;

  /// op1_A = AluOp[1] + l
  assign op1_A = ALUOp[1] | l;
  /// op2_B = AluOp[1] + AluOp[0] + l
  assign op2_B = ALUOp[1] | ALUOp[0] | l;
  /// cpl = ~l~AluOP[1] + l~AluOp[0]
  // assign cpl = (~l & ~ALUOp[1]) | (~l & ALUOp[0]);
  assign cpl = ~l & ALUOp[0];
  /// cin0 = ~AluOp[1] + AluOp[0]
  assign cin0 = ~ALUOp[1] | ALUOp[0];

  /// Primer mux
  mux2_4 mux1(op1, 4'b0, A, op1_A);
  /// Segundo mux
  mux2_4 mux2(out_mux, A, B, op2_B);
  /// Complemento a 1
  compl1 compl(op2, out_mux, cpl);
  /// Sumador completo
  sum4 sum(out1_sum, carry, op1, op2, cin0);
  /// Unidad lógica
  ul4 ul(out2_sum, op1, op2, ALUOp);
  /// Tercer mux
  mux2_4 mux3(R, out1_sum, out2_sum, l);

  /// Zero, sign y carry
  assign zero = R ? 4'b0 : 4'b1;
  assign sign = R[3];

endmodule

ALU/Implementacion/Playground/alu_tb_M1.v
// Testbench para modulo alu
`timescale 1 ns / 10 ps //Directiva que fija la unidad de tiempo de simulación y la precision de la unidad
module alu_tb;
//declaracion de señales
reg [1:0] t_Op;
reg t_l;
reg [3:0] t_A, t_B;
wire [3:0] t_R;
wire t_z, t_c, t_s;
integer errores;
//instancia del modulo a testear
alu mat(t_R, t_z, t_c, t_s, t_A, t_B, t_Op, t_l);
initial
begin
  $dumpfile("alu.vcd");
  $dumpvars;
  $monitor("tiempo=%0d A=%b B=%b L=%b Op=%b R=%b, Z=%b, C=%b, S=%b", $time, t_A, t_B, t_l, t_Op, t_R, t_z, t_c, t_s);

  errores = 0;
  t_l = 1'b0;
  repeat(2)
	begin
	t_Op = 2'b0;
	repeat(4)
		begin
		  t_A = 4'b0;
		  repeat(16) 
		  begin
			t_B = 4'b0;
			repeat(16) 
			begin
				# 2 check;
				t_B = t_B + 1;
			end
			t_A = t_A + 1;
		  end
		  t_Op = t_Op + 1;
		end
		t_l = t_l + 1;
	end
	$display("Encontradas %d operaciones erroneas", errores);
  //fin simulacion
  $finish;
end

// Tarea para hacer la comprobación automática de resultados
task check;
reg [4:0] result;
reg flag_zero, flag_carry, flag_sign;
begin
	// Si las operaciones son lógicas
	if (t_l)
	begin
		case (t_Op)
			2'b00: result[3:0] = t_A & t_B;
			2'b01: result[3:0] = t_A | t_B;
			2'b10: result[3:0] = t_A ^ t_B;
			2'b11: result[3:0] = ~t_A;
			default: $display("ERROR. Valor no esperado para t_Op: %b", t_Op);
		endcase
		flag_carry = 1'bx;
		flag_sign = 1'bx;
	end
	else
	begin
		case (t_Op)
			2'b00: result = t_A + 4'b0001;
			2'b01: result = (t_B ^4'b1111) + 4'b0001;
			2'b10: result = t_A + t_B;
			2'b11: result = t_A + ((t_B ^4'b1111) + 1);
			default: $display("ERROR. Valor no esperado para t_Op: %b", t_Op);
		endcase
		flag_carry = result[4];
		flag_sign = result[3];
		if (flag_sign !== t_s || flag_carry !== t_c)
		begin
			errores = errores + 1;
			$display("ERROR con operacion L=%b, OP=%b A=%b B=%b", t_l, t_Op, t_A, t_B);
			if (flag_sign !== t_s)
				$display("ERROR. Flag de signo esperado %b, obtenido %b", flag_sign, t_s);
			if (flag_carry !== t_c)
				$display("\tFlag de acarreo esperado %b, obtenido %b", flag_carry, t_c);
		end
	end

	flag_zero = ~| result[3:0];
	if (result[3:0] !== t_R || flag_zero !== t_z)
	begin
		errores = errores + 1;
		$display("ERROR con operacion L=%b, OP=%b A=%b B=%b", t_l, t_Op, t_A, t_B);
		if (result[3:0] !== t_R)
			$display("\tResultado esperado %b, obtenido %b", result[3:0], t_R);
		if (flag_zero !== t_z)
			$display("\tFlag de cero esperado %b, obtenido %b", flag_zero, t_z);
	end
end
endtask
endmodule

ALU/Modificacion/Test/alu.vcd
$date
	Tue Nov  8 00:20:10 2022
$end
$version
	Icarus Verilog
$end
$timescale
	10ps
$end
$scope module alu_tb $end
$var wire 1 ! t_z $end
$var wire 1 " t_s $end
$var wire 1 # t_c $end
$var wire 4 $ t_R [3:0] $end
$var reg 4 % t_A [3:0] $end
$var reg 4 & t_B [3:0] $end
$var reg 2 ' t_Op [1:0] $end
$var reg 1 ( t_l $end
$var integer 32 ) errores [31:0] $end
$scope module mat $end
$var wire 4 * A [3:0] $end
$var wire 2 + ALUOp [1:0] $end
$var wire 4 , B [3:0] $end
$var wire 1 - cin0 $end
$var wire 1 . cpl $end
$var wire 1 ( l $end
$var wire 1 / op1_A $end
$var wire 1 0 op2_B $end
$var wire 1 ! zero $end
$var wire 1 " sign $end
$var wire 4 1 out_mux [3:0] $end
$var wire 4 2 out2_sum [3:0] $end
$var wire 4 3 out1_sum [3:0] $end
$var wire 4 4 op2 [3:0] $end
$var wire 4 5 op1 [3:0] $end
$var wire 1 # carry $end
$var wire 4 6 R [3:0] $end
$scope module compl $end
$var wire 1 . cpl $end
$var wire 4 7 Out [3:0] $end
$var wire 4 8 Inp [3:0] $end
$upscope $end
$scope module mux1 $end
$var wire 4 9 A [3:0] $end
$var wire 4 : B [3:0] $end
$var wire 1 / s $end
$var wire 4 ; Out [3:0] $end
$upscope $end
$scope module mux2 $end
$var wire 4 < A [3:0] $end
$var wire 4 = B [3:0] $end
$var wire 4 > Out [3:0] $end
$var wire 1 0 s $end
$upscope $end
$scope module mux3 $end
$var wire 1 ( s $end
$var wire 4 ? Out [3:0] $end
$var wire 4 @ B [3:0] $end
$var wire 4 A A [3:0] $end
$upscope $end
$scope module sum $end
$var wire 4 B A [3:0] $end
$var wire 4 C B [3:0] $end
$var wire 1 - c_in $end
$var wire 1 # c_out $end
$var wire 1 D c3 $end
$var wire 1 E c2 $end
$var wire 1 F c1 $end
$var wire 4 G S [3:0] $end
$scope module fa0 $end
$var wire 1 H a $end
$var wire 1 I b $end
$var wire 1 - c_in $end
$var wire 1 J sum $end
$var wire 1 F c_out $end
$upscope $end
$scope module fa1 $end
$var wire 1 K a $end
$var wire 1 L b $end
$var wire 1 F c_in $end
$var wire 1 M sum $end
$var wire 1 E c_out $end
$upscope $end
$scope module fa2 $end
$var wire 1 N a $end
$var wire 1 O b $end
$var wire 1 E c_in $end
$var wire 1 P sum $end
$var wire 1 D c_out $end
$upscope $end
$scope module fa3 $end
$var wire 1 Q a $end
$var wire 1 R b $end
$var wire 1 D c_in $end
$var wire 1 S sum $end
$var wire 1 # c_out $end
$upscope $end
$upscope $end
$scope module ul $end
$var wire 4 T A [3:0] $end
$var wire 4 U B [3:0] $end
$var wire 2 V S [1:0] $end
$var wire 4 W Out [3:0] $end
$scope module cl0 $end
$var wire 2 X S [1:0] $end
$var wire 1 Y a $end
$var wire 1 Z and_out $end
$var wire 1 [ b $end
$var wire 1 \ not_out $end
$var wire 1 ] or_out $end
$var wire 1 ^ xor_out $end
$var wire 1 _ out $end
$scope module mux $end
$var wire 2 ` S [1:0] $end
$var wire 1 Z a $end
$var wire 1 ] b $end
$var wire 1 ^ c $end
$var wire 1 \ d $end
$var reg 1 _ out $end
$upscope $end
$upscope $end
$scope module cl1 $end
$var wire 2 a S [1:0] $end
$var wire 1 b a $end
$var wire 1 c and_out $end
$var wire 1 d b $end
$var wire 1 e not_out $end
$var wire 1 f or_out $end
$var wire 1 g xor_out $end
$var wire 1 h out $end
$scope module mux $end
$var wire 2 i S [1:0] $end
$var wire 1 c a $end
$var wire 1 f b $end
$var wire 1 g c $end
$var wire 1 e d $end
$var reg 1 h out $end
$upscope $end
$upscope $end
$scope module cl2 $end
$var wire 2 j S [1:0] $end
$var wire 1 k a $end
$var wire 1 l and_out $end
$var wire 1 m b $end
$var wire 1 n not_out $end
$var wire 1 o or_out $end
$var wire 1 p xor_out $end
$var wire 1 q out $end
$scope module mux $end
$var wire 2 r S [1:0] $end
$var wire 1 l a $end
$var wire 1 o b $end
$var wire 1 p c $end
$var wire 1 n d $end
$var reg 1 q out $end
$upscope $end
$upscope $end
$scope module cl3 $end
$var wire 2 s S [1:0] $end
$var wire 1 t a $end
$var wire 1 u and_out $end
$var wire 1 v b $end
$var wire 1 w not_out $end
$var wire 1 x or_out $end
$var wire 1 y xor_out $end
$var wire 1 z out $end
$scope module mux $end
$var wire 2 { S [1:0] $end
$var wire 1 u a $end
$var wire 1 x b $end
$var wire 1 y c $end
$var wire 1 w d $end
$var reg 1 z out $end
$upscope $end
$upscope $end
$upscope $end
$upscope $end
$scope task check $end
$var reg 1 | flag_carry $end
$var reg 1 } flag_sign $end
$var reg 1 ~ flag_zero $end
$var reg 5 !" result [4:0] $end
$upscope $end
$upscope $end
$enddefinitions $end
#0
$dumpvars
bx !"
x~
x}
x|
b0 {
0z
0y
0x
1w
0v
0u
0t
b0 s
b0 r
0q
0p
0o
1n
0m
0l
0k
b0 j
b0 i
0h
0g
0f
1e
0d
0c
0b
b0 a
b0 `
0_
0^
0]
1\
0[
0Z
0Y
b0 X
b0 W
b0 V
b0 U
b0 T
0S
0R
0Q
0P
0O
0N
0M
0L
0K
1J
0I
0H
b1 G
0F
0E
0D
b0 C
b0 B
b1 A
b0 @
b1 ?
b0 >
b0 =
b0 <
b0 ;
b0 :
b0 9
b0 8
b0 7
b1 6
b0 5
b0 4
b1 3
b0 2
b0 1
10
0/
0.
1-
b0 ,
b0 +
b0 *
b0 )
0(
b0 '
b0 &
b0 %
b1 $
0#
0"
0!
$end
#200
b10 $
b10 6
b10 ?
1M
b10 3
b10 A
b10 G
0J
1F
1]
1^
1I
1[
b1 4
b1 7
b1 C
b1 U
b1 1
b1 8
b1 >
b1 &
b1 ,
b1 =
0~
0}
0|
b1 !"
#400
b11 $
b11 6
b11 ?
1f
1g
b11 3
b11 A
b11 G
1J
0F
0]
0^
1L
1d
0I
0[
b10 4
b10 7
b10 C
b10 U
b10 1
b10 8
b10 >
b10 &
b10 ,
b10 =
b10 !"
#600
0!
1P
b100 $
b100 6
b100 ?
0M
1E
b100 3
b100 A
b100 G
0J
1F
1]
1^
1I
1[
b11 4
b11 7
b11 C
b11 U
b11 1
b11 8
b11 >
b11 &
b11 ,
b11 =
b11 !"
#800
b101 $
b101 6
b101 ?
1o
1p
0E
0f
0g
b101 3
b101 A
b101 G
1J
0F
0]
0^
1O
1m
0L
0d
0I
0[
b100 4
b100 7
b100 C
b100 U
b100 1
b100 8
b100 >
b100 &
b100 ,
b100 =
b100 !"
#1000
b110 $
b110 6
b110 ?
1M
b110 3
b110 A
b110 G
0J
1F
1]
1^
1I
1[
b101 4
b101 7
b101 C
b101 U
b101 1
b101 8
b101 >
b101 &
b101 ,
b101 =
b101 !"
#1200
b111 $
b111 6
b111 ?
1f
1g
b111 3
b111 A
b111 G
1J
0F
0]
0^
1L
1d
0I
0[
b110 4
b110 7
b110 C
b110 U
b110 1
b110 8
b110 >
b110 &
b110 ,
b110 =
b110 !"
#1400
1"
1S
0P
1D
b1000 $
b1000 6
b1000 ?
0M
1E
b1000 3
b1000 A
b1000 G
0J
1F
1]
1^
1I
1[
b111 4
b111 7
b111 C
b111 U
b111 1
b111 8
b111 >
b111 &
b111 ,
b111 =
b111 !"
#1600
b1001 $
b1001 6
b1001 ?
1x
1y
0D
0o
0p
0E
0f
0g
b1001 3
b1001 A
b1001 G
1J
0F
0]
0^
1R
1v
0O
0m
0L
0d
0I
0[
b1000 4
b1000 7
b1000 C
b1000 U
b1000 1
b1000 8
b1000 >
b1000 &
b1000 ,
b1000 =
1}
b1000 !"
#1800
b1010 $
b1010 6
b1010 ?
1M
b1010 3
b1010 A
b1010 G
0J
1F
1]
1^
1I
1[
b1001 4
b1001 7
b1001 C
b1001 U
b1001 1
b1001 8
b1001 >
b1001 &
b1001 ,
b1001 =
b1001 !"
#2000
b1011 $
b1011 6
b1011 ?
1f
1g
b1011 3
b1011 A
b1011 G
1J
0F
0]
0^
1L
1d
0I
0[
b1010 4
b1010 7
b1010 C
b1010 U
b1010 1
b1010 8
b1010 >
b1010 &
b1010 ,
b1010 =
b1010 !"
#2200
1P
b1100 $
b1100 6
b1100 ?
0M
1E
b1100 3
b1100 A
b1100 G
0J
1F
1]
1^
1I
1[
b1011 4
b1011 7
b1011 C
b1011 U
b1011 1
b1011 8
b1011 >
b1011 &
b1011 ,
b1011 =
b1011 !"
#2400
b1101 $
b1101 6
b1101 ?
1o
1p
0E
0f
0g
b1101 3
b1101 A
b1101 G
1J
0F
0]
0^
1O
1m
0L
0d
0I
0[
b1100 4
b1100 7
b1100 C
b1100 U
b1100 1
b1100 8
b1100 >
b1100 &
b1100 ,
b1100 =
b1100 !"
#2600
b1110 $
b1110 6
b1110 ?
1M
b1110 3
b1110 A
b1110 G
0J
1F
1]
1^
1I
1[
b1101 4
b1101 7
b1101 C
b1101 U
b1101 1
b1101 8
b1101 >
b1101 &
b1101 ,
b1101 =
b1101 !"
#2800
b1111 $
b1111 6
b1111 ?
1f
1g
b1111 3
b1111 A
b1111 G
1J
0F
0]
0^
1L
1d
0I
0[
b1110 4
b1110 7
b1110 C
b1110 U
b1110 1
b1110 8
b1110 >
b1110 &
b1110 ,
b1110 =
b1110 !"
#3000
1!
0"
0S
1#
0P
1D
b0 $
b0 6
b0 ?
0M
1E
b0 3
b0 A
b0 G
0J
1F
1]
1^
1I
1[
b1111 4
b1111 7
b1111 C
b1111 U
b1111 1
b1111 8
b1111 >
b1111 &
b1111 ,
b1111 =
b1111 !"
#3200
0!
b1 $
b1 6
b1 ?
0#
0x
0y
0D
0o
0p
0E
0f
0g
b1 3
b1 A
b1 G
1J
0F
0]
0^
0R
0v
0O
0m
0L
0d
0I
0[
b0 4
b0 7
b0 C
b0 U
b1 %
b1 *
b1 :
b1 <
b0 1
b0 8
b0 >
b0 &
b0 ,
b0 =
1~
0}
1|
b10000 !"
#3400
b10 $
b10 6
b10 ?
1M
b10 3
b10 A
b10 G
0J
1F
1]
1^
1I
1[
b1 4
b1 7
b1 C
b1 U
b1 1
b1 8
b1 >
b1 &
b1 ,
b1 =
0~
0|
b1 !"
#3600
b11 $
b11 6
b11 ?
1f
1g
b11 3
b11 A
b11 G
1J
0F
0]
0^
1L
1d
0I
0[
b10 4
b10 7
b10 C
b10 U
b10 1
b10 8
b10 >
b10 &
b10 ,
b10 =
b10 !"
#3800
0!
1P
b100 $
b100 6
b100 ?
0M
1E
b100 3
b100 A
b100 G
0J
1F
1]
1^
1I
1[
b11 4
b11 7
b11 C
b11 U
b11 1
b11 8
b11 >
b11 &
b11 ,
b11 =
b11 !"
#4000
b101 $
b101 6
b101 ?
1o
1p
0E
0f
0g
b101 3
b101 A
b101 G
1J
0F
0]
0^
1O
1m
0L
0d
0I
0[
b100 4
b100 7
b100 C
b100 U
b100 1
b100 8
b100 >
b100 &
b100 ,
b100 =
b100 !"
#4200
b110 $
b110 6
b110 ?
1M
b110 3
b110 A
b110 G
0J
1F
1]
1^
1I
1[
b101 4
b101 7
b101 C
b101 U
b101 1
b101 8
b101 >
b101 &
b101 ,
b101 =
b101 !"
#4400
b111 $
b111 6
b111 ?
1f
1g
b111 3
b111 A
b111 G
1J
0F
0]
0^
1L
1d
0I
0[
b110 4
b110 7
b110 C
b110 U
b110 1
b110 8
b110 >
b110 &
b110 ,
b110 =
b110 !"
#4600
1"
1S
0P
1D
b1000 $
b1000 6
b1000 ?
0M
1E
b1000 3
b1000 A
b1000 G
0J
1F
1]
1^
1I
1[
b111 4
b111 7
b111 C
b111 U
b111 1
b111 8
b111 >
b111 &
b111 ,
b111 =
b111 !"
#4800
b1001 $
b1001 6
b1001 ?
1x
1y
0D
0o
0p
0E
0f
0g
b1001 3
b1001 A
b1001 G
1J
0F
0]
0^
1R
1v
0O
0m
0L
0d
0I
0[
b1000 4
b1000 7
b1000 C
b1000 U
b1000 1
b1000 8
b1000 >
b1000 &
b1000 ,
b1000 =
1}
b1000 !"
#5000
b1010 $
b1010 6
b1010 ?
1M
b1010 3
b1010 A
b1010 G
0J
1F
1]
1^
1I
1[
b1001 4
b1001 7
b1001 C
b1001 U
b1001 1
b1001 8
b1001 >
b1001 &
b1001 ,
b1001 =
b1001 !"
#5200
b1011 $
b1011 6
b1011 ?
1f
1g
b1011 3
b1011 A
b1011 G
1J
0F
0]
0^
1L
1d
0I
0[
b1010 4
b1010 7
b1010 C
b1010 U
b1010 1
b1010 8
b1010 >
b1010 &
b1010 ,
b1010 =
b1010 !"
#5400
1P
b1100 $
b1100 6
b1100 ?
0M
1E
b1100 3
b1100 A
b1100 G
0J
1F
1]
1^
1I
1[
b1011 4
b1011 7
b1011 C
b1011 U
b1011 1
b1011 8
b1011 >
b1011 &
b1011 ,
b1011 =
b1011 !"
#5600
b1101 $
b1101 6
b1101 ?
1o
1p
0E
0f
0g
b1101 3
b1101 A
b1101 G
1J
0F
0]
0^
1O
1m
0L
0d
0I
0[
b1100 4
b1100 7
b1100 C
b1100 U
b1100 1
b1100 8
b1100 >
b1100 &
b1100 ,
b1100 =
b1100 !"
#5800
b1110 $
b1110 6
b1110 ?
1M
b1110 3
b1110 A
b1110 G
0J
1F
1]
1^
1I
1[
b1101 4
b1101 7
b1101 C
b1101 U
b1101 1
b1101 8
b1101 >
b1101 &
b1101 ,
b1101 =
b1101 !"
#6000
b1111 $
b1111 6
b1111 ?
1f
1g
b1111 3
b1111 A
b1111 G
1J
0F
0]
0^
1L
1d
0I
0[
b1110 4
b1110 7
b1110 C
b1110 U
b1110 1
b1110 8
b1110 >
b1110 &
b1110 ,
b1110 =
b1110 !"
#6200
1!
0"
0S
1#
0P
1D
b0 $
b0 6
b0 ?
0M
1E
b0 3
b0 A
b0 G
0J
1F
1]
1^
1I
1[
b1111 4
b1111 7
b1111 C
b1111 U
b1111 1
b1111 8
b1111 >
b1111 &
b1111 ,
b1111 =
b1111 !"
#6400
0!
b1 $
b1 6
b1 ?
0#
0x
0y
0D
0o
0p
0E
0f
0g
b1 3
b1 A
b1 G
1J
0F
0]
0^
0R
0v
0O
0m
0L
0d
0I
0[
b0 4
b0 7
b0 C
b0 U
b10 %
b10 *
b10 :
b10 <
b0 1
b0 8
b0 >
b0 &
b0 ,
b0 =
1~
0}
1|
b10000 !"
#6600
b10 $
b10 6
b10 ?
1M
b10 3
b10 A
b10 G
0J
1F
1]
1^
1I
1[
b1 4
b1 7
b1 C
b1 U
b1 1
b1 8
b1 >
b1 &
b1 ,
b1 =
0~
0|
b1 !"
#6800
b11 $
b11 6
b11 ?
1f
1g
b11 3
b11 A
b11 G
1J
0F
0]
0^
1L
1d
0I
0[
b10 4
b10 7
b10 C
b10 U
b10 1
b10 8
b10 >
b10 &
b10 ,
b10 =
b10 !"
#7000
0!
1P
b100 $
b100 6
b100 ?
0M
1E
b100 3
b100 A
b100 G
0J
1F
1]
1^
1I
1[
b11 4
b11 7
b11 C
b11 U
b11 1
b11 8
b11 >
b11 &
b11 ,
b11 =
b11 !"
#7200
b101 $
b101 6
b101 ?
1o
1p
0E
0f
0g
b101 3
b101 A
b101 G
1J
0F
0]
0^
1O
1m
0L
0d
0I
0[
b100 4
b100 7
b100 C
b100 U
b100 1
b100 8
b100 >
b100 &
b100 ,
b100 =
b100 !"
#7400
b110 $
b110 6
b110 ?
1M
b110 3
b110 A
b110 G
0J
1F
1]
1^
1I
1[
b101 4
b101 7
b101 C
b101 U
b101 1
b101 8
b101 >
b101 &
b101 ,
b101 =
b101 !"
#7600
b111 $
b111 6
b111 ?
1f
1g
b111 3
b111 A
b111 G
1J
0F
0]
0^
1L
1d
0I
0[
b110 4
b110 7
b110 C
b110 U
b110 1
b110 8
b110 >
b110 &
b110 ,
b110 =
b110 !"
#7800
1"
1S
0P
1D
b1000 $
b1000 6
b1000 ?
0M
1E
b1000 3
b1000 A
b1000 G
0J
1F
1]
1^
1I
1[
b111 4
b111 7
b111 C
b111 U
b111 1
b111 8
b111 >
b111 &
b111 ,
b111 =
b111 !"
#8000
b1001 $
b1001 6
b1001 ?
1x
1y
0D
0o
0p
0E
0f
0g
b1001 3
b1001 A
b1001 G
1J
0F
0]
0^
1R
1v
0O
0m
0L
0d
0I
0[
b1000 4
b1000 7
b1000 C
b1000 U
b1000 1
b1000 8
b1000 >
b1000 &
b1000 ,
b1000 =
1}
b1000 !"
#8200
b1010 $
b1010 6
b1010 ?
1M
b1010 3
b1010 A
b1010 G
0J
1F
1]
1^
1I
1[
b1001 4
b1001 7
b1001 C
b1001 U
b1001 1
b1001 8
b1001 >
b1001 &
b1001 ,
b1001 =
b1001 !"
#8400
b1011 $
b1011 6
b1011 ?
1f
1g
b1011 3
b1011 A
b1011 G
1J
0F
0]
0^
1L
1d
0I
0[
b1010 4
b1010 7
b1010 C
b1010 U
b1010 1
b1010 8
b1010 >
b1010 &
b1010 ,
b1010 =
b1010 !"
#8600
1P
b1100 $
b1100 6
b1100 ?
0M
1E
b1100 3
b1100 A
b1100 G
0J
1F
1]
1^
1I
1[
b1011 4
b1011 7
b1011 C
b1011 U
b1011 1
b1011 8
b1011 >
b1011 &
b1011 ,
b1011 =
b1011 !"
#8800
b1101 $
b1101 6
b1101 ?
1o
1p
0E
0f
0g
b1101 3
b1101 A
b1101 G
1J
0F
0]
0^
1O
1m
0L
0d
0I
0[
b1100 4
b1100 7
b1100 C
b1100 U
b1100 1
b1100 8
b1100 >
b1100 &
b1100 ,
b1100 =
b1100 !"
#9000
b1110 $
b1110 6
b1110 ?
1M
b1110 3
b1110 A
b1110 G
0J
1F
1]
1^
1I
1[
b1101 4
b1101 7
b1101 C
b1101 U
b1101 1
b1101 8
b1101 >
b1101 &
b1101 ,
b1101 =
b1101 !"
#9200
b1111 $
b1111 6
b1111 ?
1f
1g
b1111 3
b1111 A
b1111 G
1J
0F
0]
0^
1L
1d
0I
0[
b1110 4
b1110 7
b1110 C
b1110 U
b1110 1
b1110 8
b1110 >
b1110 &
b1110 ,
b1110 =
b1110 !"
#9400
1!
0"
0S
1#
0P
1D
b0 $
b0 6
b0 ?
0M
1E
b0 3
b0 A
b0 G
0J
1F
1]
1^
1I
1[
b1111 4
b1111 7
b1111 C
b1111 U
b1111 1
b1111 8
b1111 >
b1111 &
b1111 ,
b1111 =
b1111 !"
#9600
0!
b1 $
b1 6
b1 ?
0#
0x
0y
0D
0o
0p
0E
0f
0g
b1 3
b1 A
b1 G
1J
0F
0]
0^
0R
0v
0O
0m
0L
0d
0I
0[
b0 4
b0 7
b0 C
b0 U
b11 %
b11 *
b11 :
b11 <
b0 1
b0 8
b0 >
b0 &
b0 ,
b0 =
1~
0}
1|
b10000 !"
#9800
b10 $
b10 6
b10 ?
1M
b10 3
b10 A
b10 G
0J
1F
1]
1^
1I
1[
b1 4
b1 7
b1 C
b1 U
b1 1
b1 8
b1 >
b1 &
b1 ,
b1 =
0~
0|
b1 !"
#10000
b11 $
b11 6
b11 ?
1f
1g
b11 3
b11 A
b11 G
1J
0F
0]
0^
1L
1d
0I
0[
b10 4
b10 7
b10 C
b10 U
b10 1
b10 8
b10 >
b10 &
b10 ,
b10 =
b10 !"
#10200
0!
1P
b100 $
b100 6
b100 ?
0M
1E
b100 3
b100 A
b100 G
0J
1F
1]
1^
1I
1[
b11 4
b11 7
b11 C
b11 U
b11 1
b11 8
b11 >
b11 &
b11 ,
b11 =
b11 !"
#10400
b101 $
b101 6
b101 ?
1o
1p
0E
0f
0g
b101 3
b101 A
b101 G
1J
0F
0]
0^
1O
1m
0L
0d
0I
0[
b100 4
b100 7
b100 C
b100 U
b100 1
b100 8
b100 >
b100 &
b100 ,
b100 =
b100 !"
#10600
b110 $
b110 6
b110 ?
1M
b110 3
b110 A
b110 G
0J
1F
1]
1^
1I
1[
b101 4
b101 7
b101 C
b101 U
b101 1
b101 8
b101 >
b101 &
b101 ,
b101 =
b101 !"
#10800
b111 $
b111 6
b111 ?
1f
1g
b111 3
b111 A
b111 G
1J
0F
0]
0^
1L
1d
0I
0[
b110 4
b110 7
b110 C
b110 U
b110 1
b110 8
b110 >
b110 &
b110 ,
b110 =
b110 !"
#11000
1"
1S
0P
1D
b1000 $
b1000 6
b1000 ?
0M
1E
b1000 3
b1000 A
b1000 G
0J
1F
1]
1^
1I
1[
b111 4
b111 7
b111 C
b111 U
b111 1
b111 8
b111 >
b111 &
b111 ,
b111 =
b111 !"
#11200
b1001 $
b1001 6
b1001 ?
1x
1y
0D
0o
0p
0E
0f
0g
b1001 3
b1001 A
b1001 G
1J
0F
0]
0^
1R
1v
0O
0m
0L
0d
0I
0[
b1000 4
b1000 7
b1000 C
b1000 U
b1000 1
b1000 8
b1000 >
b1000 &
b1000 ,
b1000 =
1}
b1000 !"
#11400
b1010 $
b1010 6
b1010 ?
1M
b1010 3
b1010 A
b1010 G
0J
1F
1]
1^
1I
1[
b1001 4
b1001 7
b1001 C
b1001 U
b1001 1
b1001 8
b1001 >
b1001 &
b1001 ,
b1001 =
b1001 !"
#11600
b1011 $
b1011 6
b1011 ?
1f
1g
b1011 3
b1011 A
b1011 G
1J
0F
0]
0^
1L
1d
0I
0[
b1010 4
b1010 7
b1010 C
b1010 U
b1010 1
b1010 8
b1010 >
b1010 &
b1010 ,
b1010 =
b1010 !"
#11800
1P
b1100 $
b1100 6
b1100 ?
0M
1E
b1100 3
b1100 A
b1100 G
0J
1F
1]
1^
1I
1[
b1011 4
b1011 7
b1011 C
b1011 U
b1011 1
b1011 8
b1011 >
b1011 &
b1011 ,
b1011 =
b1011 !"
