ALU/Modificacion/mux4_1.v
/// Multiplexor 4 a 1 con entradas de 1 bit
/// Forma: conductual (reg)
module mux4_1(output reg out, input wire a, b, c, d, input wire [1:0] S);
  /// Lista de sensibilidad
  always @(a or b or c or d or S) 
  /// No hace falta begin y end porque el always contiene una sola sentencia, el case
    case (S)  
      /// Dos bits en binario            
      2'b00: out = a;
      2'b01: out = b;
      2'b10: out = c;
      2'b11: out = d;
      default: out = 'bx; /// Desconocido en cualquier otro caso                   
    endcase
endmodule

/// Forma estructural (wire)
// module mux4_1(output wire out, input wire a, b, c, d, input wire [1:0] S);
//   assign out = S[1] ? (S[0] ? d : c) : (S[0] ? b : a);
//   /// Si S[1] es 0, se seleccionan las primeras dos entradas
//   /// Si S[1] es 1, se seleccionan las otras dos entradas
//   /// Si S[0] es 0, se selecciona la primera de las dos seleccionadas
// endmodule

ALU/Implementacion/cl.v
/// Celda lógica
/// Estructural (wire)
module cl(output wire out, input wire a, b, input wire [1:0] S);
  /// Cables de salidas
  wire and_out, or_out, xor_out, not_out;
  /// Operaciones
  and and1(and_out, a, b);
  or or1(or_out, a, b);
  xor xor1(xor_out, a, b);
  not not1(not_out, a);
  /// Multiplexor para selecionar
  mux4_1 mux(out, and_out, or_out, xor_out, not_out, S);
endmodule

/// Forma conductual (reg)

ALU/Modificacion/Test/cl_tb.v
/// ` Esa cosa significa directiva de verilog
/// Es para los retardos
/// Unidad de tiempo con la que se leen los retardos
/// Escala / Precisión
/// Por debajo de precisión no va a detectar cambios
`timescale 1 ns / 10 ps

/// NO tiene entradas ni salidas
module cl_tb; 

/// Son reg porque les damos valor dentro de una estructura
/// Es reg porque es conductual
reg [1:0] test_S;
reg test_a, test_b; 
/// No tiene que ver con el otro fichero
/// Es wire porque es estructual
wire test_out;

/// Módulo que queremos probar
cl cl(test_out, test_a, test_b, test_S); 

/// Probamos todas las combinaciones
/// Initial ejecuta todos en paralelo nada más empezar la simulación
/// Always ejecuta todo el rato
/// Podríamos tener varios initial
initial 
begin
  /// Es como un print
  /// Cada vez que cambia el valor de alguna señal, imprime
  $monitor("a(%b) b(%b) S(%b) out(%b)", test_a, test_b, test_S, test_out);
  /// Estos dos son para visualizar
  /// dumpfile: traza
  /// dumpvars: qué queremos guardar en la traza (sin nada, guarda todo)
  /// Comando: gtkwave ejemplo_tb.vcd &
  $dumpfile("cl_tb.vcd");
  $dumpvars;

  /// And: S = 00
  test_S = 2'b00;
  /// Test: a = 0; b = 0
  test_a = 1'b0;
  test_b = 1'b0;
  #20; /// Retardo (20 x 1)
  /// Test: a = 1; b = 0
  test_a = 1'b1;
  test_b = 1'b0;
  #20; /// Retardo (20 x 1)
  /// Test: a = 1; b = 1
  test_a = 1'b1;
  test_b = 1'b1;
  #20; /// Retardo (20 x 1)

  /// Or: S = 01
  test_S = 2'b01;
  /// Test: a = 0; b = 0
  test_a = 1'b0;
  test_b = 1'b0;
  #20; /// Retardo (20 x 1)
  /// Test: a = 0; b = 1
  test_a = 1'b0;
  test_b = 1'b1;
  #20; /// Retardo (20 x 1)
  /// Test: a = 1; b = 1
  test_a = 1'b1;
  test_b = 1'b1;
  #20; /// Retardo (20 x 1)

  /// Xor: S = 10
  test_S = 2'b10;
  /// Test: a = 0; b = 0
  test_a = 1'b0;
  test_b = 1'b0;
  #20; /// Retardo (20 x 1)
  /// Test: a = 0; b = 1
  test_a = 1'b0;
  test_b = 1'b1;
  #20; /// Retardo (20 x 1)
  /// Test: a = 1; b = 1
  test_a = 1'b1;
  test_b = 1'b1;
  #20; /// Retardo (20 x 1)

  /// Not: S = 11
  test_S = 2'b11;
  /// Test: a = 0
  test_a = 1'b0;
  #20; /// Retardo (20 x 1)
  /// Test: a = 1
  test_a = 1'b1;
  #20; /// Retardo (20 x 1)

  /// Todos los comandos internos de verilog tienen un $
  /// Si no lo ponemos, no salimos del entorno
  $finish;  

end
endmodule

ALU/Modificacion/Test/cl_tb.vcd
$date
	Mon Oct 31 00:57:06 2022
$end
$version
	Icarus Verilog
$end
$timescale
	10ps
$end
$scope module cl_tb $end
$var wire 1 ! test_out $end
$var reg 2 " test_S [1:0] $end
$var reg 1 # test_a $end
$var reg 1 $ test_b $end
$scope module cl $end
$var wire 2 % S [1:0] $end
$var wire 1 # a $end
$var wire 1 & and_out $end
$var wire 1 $ b $end
$var wire 1 ' not_out $end
$var wire 1 ( or_out $end
$var wire 1 ) xor_out $end
$var wire 1 ! out $end
$scope module mux $end
$var wire 2 * S [1:0] $end
$var wire 1 & a $end
$var wire 1 ( b $end
$var wire 1 ) c $end
$var wire 1 ' d $end
$var reg 1 ! out $end
$upscope $end
$upscope $end
$upscope $end
$enddefinitions $end
#0
$dumpvars
b0 *
0)
0(
1'
0&
b0 %
0$
0#
b0 "
0!
$end
#2000
1(
1)
0'
1#
#4000
1!
1&
0)
1$
#6000
0!
0&
0(
1'
0$
0#
b1 "
b1 %
b1 *
#8000
1!
1(
1)
1$
#10000
1&
0)
0'
1#
#12000
0&
0(
1'
0!
0$
0#
b10 "
b10 %
b10 *
#14000
1!
1(
1)
1$
#16000
0!
1&
0)
0'
1#
#18000
1!
0&
1)
1'
0#
b11 "
b11 %
b11 *
#20000
0!
1&
0)
0'
1#
